bmp280/__init__.py
bmp280/bmp280.py
bmp280/filter.py
bmp280/pressure_oversampling.py
bmp280/sampling_interval.py
bmp280/temperature_oversampling.py
bmp280_spi_RPi-0.1.0.dist-info/LICENSE.md
bmp280_spi_RPi-0.1.0.dist-info/METADATA
bmp280_spi_RPi-0.1.0.dist-info/WHEEL
bmp280_spi_RPi-0.1.0.dist-info/top_level.txt
bmp280_spi_RPi-0.1.0.dist-info/RECORD
