Metadata-Version: 2.1
Name: bmp280-spi-RPi
Version: 0.1.0
Summary: BMP280 package for Raspberry Pi using SPI interface provided by spidev library
Author: Michal Tomek
License: # Released under MIT License
Project-URL: Homepage, https://github.com/Thugmek/BMP280-SPI-RPi
Keywords: BMP280,SPI,RPi,Raspberry,Pi
License-File: LICENSE.md
Requires-Dist: spidev
